model_trainer_app/__init__.py
model_trainer_app/app.py
model_trainer_app/auth.py
model_trainer_app_0.2.0-0.1.0.dist-info/METADATA
model_trainer_app_0.2.0-0.1.0.dist-info/WHEEL
model_trainer_app_0.2.0-0.1.0.dist-info/entry_points.txt
model_trainer_app_0.2.0-0.1.0.dist-info/top_level.txt
model_trainer_app_0.2.0-0.1.0.dist-info/RECORD
